trajectron/__init__.py
trajectron/argument_parser.py
trajectron/test_online.py
trajectron/train.py
trajectron/environment/__init__.py
trajectron/environment/data_structures.py
trajectron/environment/data_utils.py
trajectron/environment/environment.py
trajectron/environment/map.py
trajectron/environment/node.py
trajectron/environment/node_type.py
trajectron/environment/scene.py
trajectron/environment/scene_graph.py
trajectron/evaluation/__init__.py
trajectron/evaluation/evaluation.py
trajectron/model/__init__.py
trajectron/model/mgcvae.py
trajectron/model/model_registrar.py
trajectron/model/model_utils.py
trajectron/model/trajectron.py
trajectron/model/components/__init__.py
trajectron/model/components/additive_attention.py
trajectron/model/components/discrete_latent.py
trajectron/model/components/gmm2d.py
trajectron/model/components/graph_attention.py
trajectron/model/components/map_encoder.py
trajectron/model/dataset/__init__.py
trajectron/model/dataset/dataset.py
trajectron/model/dataset/homography_warper.py
trajectron/model/dataset/preprocessing.py
trajectron/model/dynamics/__init__.py
trajectron/model/dynamics/dynamic.py
trajectron/model/dynamics/linear.py
trajectron/model/dynamics/single_integrator.py
trajectron/model/dynamics/unicycle.py
trajectron/model/online/__init__.py
trajectron/model/online/online_mgcvae.py
trajectron/model/online/online_trajectron.py
trajectron/test/__init__.py
trajectron/test/test_data_structures.py
trajectron/utils/__init__.py
trajectron/utils/matrix_utils.py
trajectron/utils/os_utils.py
trajectron/utils/trajectory_utils.py
trajectron/visualization/__init__.py
trajectron/visualization/visualization.py
trajectron/visualization/visualization_utils.py
trajectron-0.1.3.dist-info/LICENSE
trajectron-0.1.3.dist-info/METADATA
trajectron-0.1.3.dist-info/WHEEL
trajectron-0.1.3.dist-info/top_level.txt
trajectron-0.1.3.dist-info/RECORD
