Metadata-Version: 2.1
Name: trajectron
Version: 0.1.3
Summary: A unofficial library for the Trajectron++ method, proposed by Tim Salzmann, Boris Ivanovic, Punarjay Chakravarty, and Marco Pavone in the entitled paper Trajectron++: Dynamically-Feasible Trajectory Forecasting With Heterogeneous Data.
Home-page: https://github.com/StanfordASL/Trajectron-plus-plus
Author: Matheus Vargas Volpon Berto
Author-email: matheusvolpon.berto@gmail.com
License: MIT
Platform: UNKNOWN
Classifier: Programming Language :: Python :: 3
Classifier: License :: OSI Approved :: MIT License
Classifier: Operating System :: OS Independent
Requires-Python: >=3.6
License-File: LICENSE
Requires-Dist: matplotlib
Requires-Dist: numpy (==1.16.4)
Requires-Dist: pandas (==0.25.1)
Requires-Dist: scipy (==1.3.1)
Requires-Dist: seaborn (==0.9.0)
Requires-Dist: tensorboard (==1.14.0)
Requires-Dist: tensorboardX (==1.8)
Requires-Dist: tensorflow (==1.14.0)
Requires-Dist: tensorflow-estimator (==1.14.0)
Requires-Dist: torch (==1.4.0)
Requires-Dist: pyquaternion (==0.9.5)
Requires-Dist: pytest (==5.3.0)
Requires-Dist: orjson (==2.1.4)
Requires-Dist: ncls (==0.0.51)
Requires-Dist: dill (==0.3.1.1)
Requires-Dist: tqdm (==4.45.0)
Requires-Dist: notebook (==6.0.3)
Requires-Dist: scikit-learn (==0.22.1)
Requires-Dist: opencv-python (==4.1.1.26)
Requires-Dist: nuscenes-devkit (==1.0.6)
